{
  "kind": "collectionType",
  "collectionName": "products",
  "info": {
    "singularName": "product",
    "pluralName": "products",
    "displayName": "product",
    "description": ""
  },
  "options": {
    "draftAndPublish": true
  },
  "pluginOptions": {},
  "attributes": {
    "name": {
      "type": "string",
      "required": true
    },
    "price": {
      "type": "decimal"
    },
    "description": {
      "type": "richtext",
      "required": true
    },
    "category": {
      "type": "string",
      "required": true
    },
    "images": {
      "type": "json",
      "required": true
    }
  }
}
